lazypr/__init__.py
lazypr/config.py
lazypr/github_api.py
lazypr/jira_api.py
lazypr/main.py
lazypr/pull_request.py
lazypr/utils.py
tests/__init__.py
tests/test_config.py
lazypr-0.1.4.dist-info/METADATA
lazypr-0.1.4.dist-info/WHEEL
lazypr-0.1.4.dist-info/entry_points.txt
lazypr-0.1.4.dist-info/top_level.txt
lazypr-0.1.4.dist-info/RECORD
