Metadata-Version: 2.1
Name: lazypr
Version: 0.1.4
Summary: Tool for creating and updating pull requests on GitHub.
Home-page: https://github.com/sanjaz/lazypr
Author: Sanja Segan
Author-email: sanjazivotic@gmail.com
License: UNKNOWN
Platform: UNKNOWN
Requires-Dist: PyGithub
Requires-Dist: pygit2
